octarine_navis_plugin/__init__.py
octarine_navis_plugin/__version__.py
octarine_navis_plugin/objects.py
octarine_navis_plugin/utils.py
octarine_navis_plugin-0.1.5.dist-info/licenses/LICENSE
octarine_navis_plugin-0.1.5.dist-info/METADATA
octarine_navis_plugin-0.1.5.dist-info/WHEEL
octarine_navis_plugin-0.1.5.dist-info/entry_points.txt
octarine_navis_plugin-0.1.5.dist-info/top_level.txt
octarine_navis_plugin-0.1.5.dist-info/RECORD
