Metadata-Version: 2.4
Name: octarine-navis-plugin
Version: 0.1.5
Summary: Octarine plugin to visualize NAVis data in 3D.
Home-page: https://github.com/navis-org/octarine-navis-plugin
Author: Philipp Schlegel
Author-email: pms70@cam.ac.uk
License: GPLv3
Project-URL: Documentation, https://github.com/navis-org/octarine-navis-plugin
Project-URL: Source, https://github.com/navis-org/octarine-navis-plugin
Project-URL: Changelog, https://github.com/navis-org/octarine-navis-plugin/releases
Keywords: octarine navis 3D visualization
Classifier: Development Status :: 3 - Alpha
Classifier: Intended Audience :: Science/Research
Classifier: Topic :: Scientific/Engineering :: Bio-Informatics
Classifier: Programming Language :: Python :: 3
Classifier: Programming Language :: Python :: 3.8
Classifier: Programming Language :: Python :: 3.9
Classifier: Programming Language :: Python :: 3.10
Classifier: Programming Language :: Python :: 3.11
Requires-Python: >=3.8
License-File: LICENSE
Requires-Dist: numpy
Requires-Dist: pandas
Dynamic: author
Dynamic: author-email
Dynamic: classifier
Dynamic: description
Dynamic: description-content-type
Dynamic: home-page
Dynamic: keywords
Dynamic: license
Dynamic: license-file
Dynamic: project-url
Dynamic: requires-dist
Dynamic: requires-python
Dynamic: summary
